Metadata-Version: 1.0
Name: SeqWORDS
Version: 0.0.2
Summary: An unsupervised Chinese word segmentation
Home-page: https://github.com/kkuanhui/SeqWORDS
Author: Harry Wu
Author-email: tf00604520@gmail.com
License: MIT Licence
Keywords: EM algorithm,unsupervised method,WDM,Chinese word segmentation
Platform: UNKNOWN
